{
  "appVersion": "99.4.35",
  "displayVersion": "V99.4.35",
  "versionName": "AP22F1B – Seitenkopf- und Redundanzbereinigung",
  "schemaVersion": 5,
  "dataLayerContractVersion": 1,
  "snapshotScope": "billingSnapshot",
  "basedOn": "99.4.34-AP22F1A-Globales-Schalenfundament",
  "releaseDate": "2026-07-17",
  "runtime": [
    "HTML",
    "CSS",
    "JavaScript"
  ],
  "framework": null,
  "buildSystem": null,
  "nextWorkPackage": "Nächstes UI-Arbeitspaket nach gesonderter Bestandsanalyse, Planung und Freigabe",
  "objectStandardVersion": 1,
  "billingSnapshotVersion": 2,
  "meterMasterStandardVersion": 1,
  "meterReadingStandardVersion": 1,
  "meterPeriodStandardVersion": 1,
  "meterAssignmentStandardVersion": 1,
  "meterReplacementStandardVersion": 1,
  "architectureVersion": 3,
  "compatibilityLayerVersion": 3,
  "uiControllerVersion": 1,
  "uiEventContractVersion": 1,
  "navigationDesignSystemVersion": 6,
  "appOrchestrationVersion": 1,
  "stateOwnershipVersion": 1,
  "runtimeDiagnosticsVersion": 1,
  "documentLayoutVersion": 4,
  "uiVisualSystemVersion": 4,
  "meterInventoryDummyVersion": 1,
  "pwaCacheName": "nk-pro-v99-4-35-ap22f1b",
  "releaseHardeningVersion": 1,
  "releaseContentPolicyVersion": 1,
  "transientUiResetVersion": 1,
  "areaDashboardVersion": 2,
  "globalBillingContextVersion": 3,
  "briefPreviewZoomVersion": 1,
  "buttonSystemVersion": 1,
  "brandAssetVersion": 1,
  "responsivePolishVersion": 1,
  "controlledBillingContextVersion": 1,
  "billingReadOnlyModeVersion": 1,
  "productiveDashboardVersion": 1,
  "statusRuleVersion": 1,
  "navigationSeparatorCleanupVersion": 1,
  "centralQualityRuleRegistryVersion": 1,
  "centralQualityResultModelVersion": 1,
  "qualityConfirmationFingerprintVersion": 1,
  "systemDiagnosticsSeparationVersion": 1,
  "priorYearPlausibilityVersion": 1,
  "meterInputLiveCalculationVersion": 1,
  "meterInputLocaleNumberVersion": 1,
  "assetCacheBustVersion": 1,
  "serviceWorkerForcedUpdateVersion": 1,
  "runtimeBuildId": "99.4.35-ap22f1b",
  "uiConsolidationVersion": 1,
  "individualValuesPageVersion": 3,
  "navigationTerminologyVersion": 1,
  "globalSpacingGridVersion": 1,
  "navigationStructureVersion": 2,
  "uiDesignSystemVersion": 5,
  "uiComponentCatalogVersion": 4,
  "uiMigrationMatrixVersion": 5,
  "uiBaseComponentsMigrationVersion": 1,
  "uiTablesListsMigrationVersion": 1,
  "uiDialogsStatesMigrationVersion": 1,
  "globalShellFoundationVersion": 1,
  "pageHeaderSystemVersion": 2,
  "uiUxContractVersion": 3,
  "pageHeaderCleanupVersion": 1
}
